devplayer/__init__.py
devplayer/__main__.py
devplayer/songs.py
devplayer-0.1.2.dist-info/LICENSE
devplayer-0.1.2.dist-info/METADATA
devplayer-0.1.2.dist-info/WHEEL
devplayer-0.1.2.dist-info/entry_points.txt
devplayer-0.1.2.dist-info/top_level.txt
devplayer-0.1.2.dist-info/RECORD
