Metadata-Version: 2.1
Name: devplayer
Version: 0.1.2
Summary: CLI for playing music and creating playlists
Home-page: https://github.com/Devansh3712/DevPlayer
Author: Devansh Singh
Author-email: devanshamity@gmail.com
License: MIT
Platform: UNKNOWN
Classifier: Programming Language :: Python :: 3
Classifier: License :: OSI Approved :: MIT License
Classifier: Operating System :: OS Independent
Requires-Dist: click (==7.1.2)
Requires-Dist: colorama (==0.4.4)
Requires-Dist: halo (==0.0.31)
Requires-Dist: log-symbols (==0.0.14)
Requires-Dist: playsound (==1.2.2)
Requires-Dist: six (==1.16.0)
Requires-Dist: spinners (==0.0.24)
Requires-Dist: termcolor (==1.1.0)
Requires-Dist: youtube-dl (==2021.4.26)
